<?xml version="1.0" encoding="UTF-8"?>
<!--
    Copyright (C) 2007-2011  BlueXML - www.bluexml.com

    This program is free software: you can redistribute it and/or modify
    it under the terms of the GNU General Public License as published by
    the Free Software Foundation, either version 3 of the License, or
    (at your option) any later version.

    This program is distributed in the hope that it will be useful,
    but WITHOUT ANY WARRANTY; without even the implied warranty of
    MERCHANTABILITY or FITNESS FOR A PARTICULAR PURPOSE.  See the
    GNU General Public License for more details.

    You should have received a copy of the GNU General Public License
    along with this program.  If not, see <http://www.gnu.org/licenses/>.

-->


<feature id="com.bluexml.side.Deployer.alfresco.feature" label="SIDE Alfresco Deployer" version="1.0.49.v20461-20100922" provider-name="BlueXML">
  <description url="http://www.bluexml.com">SIDE MDA environment eases the deployment of generated or developed extensions on specialized
frameworks like Alfresco. This feature allows to deploy extensions on Alfresco instances using Alfresco deployment standard procedure.</description>
  <copyright url="http://www.example.com/copyright">[Enter Copyright Description here.]</copyright>
  <license url="http://www.example.com/license">[Enter License Description here.]</license>
  <requires>
    <import plugin="org.eclipse.core.runtime" />
    <import plugin="org.eclipse.core.resources" />
    <import plugin="com.bluexml.side.Util.generator" />
    <import plugin="com.bluexml.side.Application" version="1.0.8" match="greaterOrEqual" />
    <import plugin="com.bluexml.side.Util.deployer" version="1.0.8" match="greaterOrEqual" />
    <import plugin="com.bluexml.side.Util.security" version="1.0.8" match="greaterOrEqual" />
    <import plugin="com.bluexml.side.Util.deployer.war" version="1.0.0" match="greaterOrEqual" />
    <import plugin="com.bluexml.side.Util.libs" version="1.0.12" match="greaterOrEqual" />
    <import plugin="com.bluexml.side.Util.componentMonitor" />
    <import plugin="com.bluexml.side.Util.log" />
  </requires>
  <plugin id="com.bluexml.side.Deployer.alfresco" download-size="0" install-size="0" version="1.0.59.v20461-20100922" unpack="false" />
</feature>

